receipts/__init__.py
receipts/admin.py
receipts/apps.py
receipts/models.py
receipts/tests.py
receipts/urls.py
receipts/views.py
receipts/migrations/0001_initial.py
receipts/migrations/__init__.py
testpack_django_receipts-1.0.7.dist-info/METADATA
testpack_django_receipts-1.0.7.dist-info/WHEEL
testpack_django_receipts-1.0.7.dist-info/top_level.txt
testpack_django_receipts-1.0.7.dist-info/RECORD
